[
  {
    "id": 1872295,
    "language_code": "en",
    "content": "With regard to the learning society, as I mentioned earlier, optimistically, people from all walks of life should be able to have equal access to education according to their needs and potentials.",
    "url": "https://quotepark.com/quotes/1872295-sukavich-rangsitpol-with-regard-to-the-learning-society-as-i-mentione/",
    "originator": {
      "id": 218988,
      "name": "Sukavich Rangsitpol",
      "url": "https://quotepark.com/authors/sukavich-rangsitpol/"
    },
    "tags": [
      "Life",
      "People",
      "Education",
      "Learning",
      "access",
      "accord",
      "accordance",
      "equal",
      "equality",
      "mention",
      "need",
      "optimist",
      "potential",
      "regard",
      "society",
      "walk",
      "walking"
    ]
  },
  {
    "id": 837130,
    "language_code": "en",
    "content": "Let everything happen to you: beauty and terror. Just keep going. No feeling is final.",
    "url": "https://quotepark.com/quotes/837130-rainer-maria-rilke-let-everything-happen-to-you-beauty-and-terror-j/",
    "originator": {
      "id": 127321,
      "name": "Rainer Maria Rilke",
      "url": "https://quotepark.com/authors/rainer-maria-rilke/"
    },
    "tags": [
      "Beauty",
      "everything",
      "feel",
      "final",
      "going",
      "happening",
      "keep",
      "terror",
      "terrorism"
    ]
  },
  {
    "id": 2107382,
    "language_code": "en",
    "content": "The chance to overcome another challenge is simply, as I always feel, a blessing.",
    "url": "https://quotepark.com/quotes/2107382-yuzuru-hanyu-the-chance-to-overcome-another-challenge-is-simply/",
    "originator": {
      "id": 283857,
      "name": "Yuzuru Hanyu",
      "url": "https://quotepark.com/authors/yuzuru-hanyu/"
    },
    "tags": [
      "Feeling",
      "Chance",
      "blessing",
      "challenge",
      "feel"
    ]
  },
  {
    "id": 1831556,
    "language_code": "en",
    "content": "Give me your body and let me love you like I do\r\nCome a little closer and let me do those things to you\r\nThis feeling will last forever, baby, that's the truth\r\nLet me be your man so I can love you",
    "url": "https://quotepark.com/quotes/1831556-zayn-malik-give-me-your-body-and-let-me-love-you-like-i-do-c/",
    "originator": {
      "id": 215319,
      "name": "Zayn Malik",
      "url": "https://quotepark.com/authors/zayn-malik/"
    },
    "tags": [
      "Love",
      "Truth",
      "Feeling",
      "Baby",
      "body",
      "can",
      "doing",
      "feel",
      "forever",
      "last",
      "likeness",
      "man",
      "thing"
    ]
  },
  {
    "id": 1395531,
    "language_code": "en",
    "content": "My pain may be the reason for somebody's laugh.\nBut my laugh must never be the reason for somebody's pain.",
    "url": "https://quotepark.com/quotes/1395531-charlie-chaplin-my-pain-may-be-the-reason-for-somebodys-laugh-bu/",
    "originator": {
      "id": 131272,
      "name": "Charlie Chaplin",
      "url": "https://quotepark.com/authors/charlie-chaplin/"
    },
    "tags": [
      "Pain",
      "laugh",
      "reason",
      "somebody",
      "Relationship"
    ]
  }
]
